{
  "data": {
    "article": {},
    "attachments": {},
    "author_id": "1766858890636120064",
    "conversation_id": "2038273740048568488",
    "created_at": "2026-03-29T15:15:03.000Z",
    "edit_controls": {
      "editable_until": "2026-03-29T16:15:03.000Z",
      "edits_remaining": 5,
      "is_edit_eligible": true
    },
    "edit_history_tweet_ids": [
      "2038273740048568488"
    ],
    "entities": {
      "urls": [
        {
          "display_url": "x.com/linyue7523/sta…",
          "end": 166,
          "expanded_url": "https://twitter.com/linyue7523/status/2038223745291297049",
          "start": 143,
          "url": "https://t.co/E7bknzlHVo"
        }
      ]
    },
    "geo": {},
    "id": "2038273740048568488",
    "lang": "zh",
    "note_tweet": {
      "entities": {}
    },
    "possibly_sensitive": false,
    "public_metrics": {
      "bookmark_count": 0,
      "impression_count": 0,
      "like_count": 0,
      "quote_count": 0,
      "reply_count": 0,
      "retweet_count": 0
    },
    "referenced_tweets": [
      {
        "id": "2038223745291297049",
        "type": "quoted"
      }
    ],
    "reply_settings": "everyone",
    "text": "我想询问一下说志愿者做得不好的人，你们有没有想过在当今互联网的舆论环境下，如果直接说了受害者为跨性别女性那么舆论会变成什么样子？\n如果没有想过，那我可以告诉你们，受害者将被评论区打上“好死”“应该的”“最支持机构的一集”之类的话语\n为受害者发声的评论区会变成一场受害者有罪论的狂欢圣宴 https://t.co/E7bknzlHVo"
  },
  "includes": {
    "media": [
      {
        "height": 2048,
        "media_key": "3_2038223737858965504",
        "public_metrics": {},
        "type": "photo",
        "url": "https://pbs.twimg.com/media/HEk5sMvaQAAOJNY.jpg",
        "width": 943
      },
      {
        "height": 2048,
        "media_key": "3_2038223737875746816",
        "public_metrics": {},
        "type": "photo",
        "url": "https://pbs.twimg.com/media/HEk5sMzaUAAHrt1.jpg",
        "width": 943
      },
      {
        "height": 2048,
        "media_key": "3_2038223737871650816",
        "public_metrics": {},
        "type": "photo",
        "url": "https://pbs.twimg.com/media/HEk5sMyb0AAMDLR.jpg",
        "width": 943
      }
    ],
    "tweets": [
      {
        "article": {},
        "attachments": {},
        "author_id": "1766858890636120064",
        "conversation_id": "2038273740048568488",
        "created_at": "2026-03-29T15:15:03.000Z",
        "edit_controls": {
          "editable_until": "2026-03-29T16:15:03.000Z",
          "edits_remaining": 5,
          "is_edit_eligible": true
        },
        "edit_history_tweet_ids": [
          "2038273740048568488"
        ],
        "entities": {
          "urls": [
            {
              "display_url": "x.com/linyue7523/sta…",
              "end": 166,
              "expanded_url": "https://twitter.com/linyue7523/status/2038223745291297049",
              "start": 143,
              "url": "https://t.co/E7bknzlHVo"
            }
          ]
        },
        "geo": {},
        "id": "2038273740048568488",
        "lang": "zh",
        "note_tweet": {
          "entities": {}
        },
        "possibly_sensitive": false,
        "public_metrics": {
          "bookmark_count": 0,
          "impression_count": 0,
          "like_count": 0,
          "quote_count": 0,
          "reply_count": 0,
          "retweet_count": 0
        },
        "referenced_tweets": [
          {
            "id": "2038223745291297049",
            "type": "quoted"
          }
        ],
        "reply_settings": "everyone",
        "text": "我想询问一下说志愿者做得不好的人，你们有没有想过在当今互联网的舆论环境下，如果直接说了受害者为跨性别女性那么舆论会变成什么样子？\n如果没有想过，那我可以告诉你们，受害者将被评论区打上“好死”“应该的”“最支持机构的一集”之类的话语\n为受害者发声的评论区会变成一场受害者有罪论的狂欢圣宴 https://t.co/E7bknzlHVo"
      },
      {
        "article": {},
        "attachments": {
          "media_keys": [
            "3_2038223737858965504",
            "3_2038223737875746816",
            "3_2038223737871650816"
          ]
        },
        "author_id": "1766858890636120064",
        "conversation_id": "2038223745291297049",
        "created_at": "2026-03-29T11:56:23.000Z",
        "edit_controls": {
          "editable_until": "2026-03-29T12:56:23.000Z",
          "edits_remaining": 5,
          "is_edit_eligible": false
        },
        "edit_history_tweet_ids": [
          "2038223745291297049"
        ],
        "entities": {
          "urls": [
            {
              "display_url": "pic.x.com/u7BK1pVRlw",
              "end": 163,
              "expanded_url": "https://x.com/Linyue7523/status/2038223745291297049/photo/1",
              "media_key": "3_2038223737858965504",
              "start": 140,
              "url": "https://t.co/u7BK1pVRlw"
            },
            {
              "display_url": "pic.x.com/u7BK1pVRlw",
              "end": 163,
              "expanded_url": "https://x.com/Linyue7523/status/2038223745291297049/photo/1",
              "media_key": "3_2038223737875746816",
              "start": 140,
              "url": "https://t.co/u7BK1pVRlw"
            },
            {
              "display_url": "pic.x.com/u7BK1pVRlw",
              "end": 163,
              "expanded_url": "https://x.com/Linyue7523/status/2038223745291297049/photo/1",
              "media_key": "3_2038223737871650816",
              "start": 140,
              "url": "https://t.co/u7BK1pVRlw"
            }
          ]
        },
        "geo": {},
        "id": "2038223745291297049",
        "lang": "zh",
        "note_tweet": {
          "entities": {}
        },
        "possibly_sensitive": false,
        "public_metrics": {
          "bookmark_count": 1,
          "impression_count": 1140,
          "like_count": 16,
          "quote_count": 4,
          "reply_count": 3,
          "retweet_count": 3
        },
        "reply_settings": "everyone",
        "text": "关于聚贤崇本受害者的事情，有很多人说受害者是女性是她最后的尊严，那么我们应该卡在这个问题上争个几天甚至几个月吗？\n我们知道受害者不是男性，但在一个走了刑事流程具备司法效力的案件里，我们不得不依据外界的客观视角来描述\n这个事情里真正该被谴责是酿造悲剧的扭转机构，而不是我们的志愿者 https://t.co/u7BK1pVRlw"
      }
    ],
    "users": [
      {
        "created_at": "2024-03-10T16:09:34.000Z",
        "description": "对每个人保持善意，愿每个人都能被世界温柔的对待/摄影📷/东方Project",
        "id": "1766858890636120064",
        "name": "Die Iris",
        "pinned_tweet_id": "2037971287851892845",
        "profile_image_url": "https://pbs.twimg.com/profile_images/2014974017019535361/pXcdgBH7_normal.jpg",
        "protected": false,
        "public_metrics": {
          "followers_count": 3716,
          "following_count": 1538,
          "like_count": 20960,
          "listed_count": 2,
          "media_count": 338,
          "tweet_count": 2977
        },
        "username": "Linyue7523",
        "verified": false
      }
    ]
  }
}